<?xml version="1.0" encoding="UTF-8"?><fr:recipe xmlns:fr="http://fruschtique.de/ns/recipe" xmlns:xsi="http://www.w3.org/2001/XMLSchema-instance" xsi:schemaLocation="http://fruschtique.de/ns/recipe file:///c:/Users/nlutt/Documents/websites/tools/recipe.xsd" rcpID="A-063">
<fr:meta><fr:book>KochbuchHD</fr:book><fr:chapter>00 Allgemeine Regeln</fr:chapter></fr:meta><fr:recipeName>Ein gutes Kartoffelmehl zu bereiten</fr:recipeName><fr:recipeKeywords/><fr:recipeIntro/><fr:recipeIngredients><fr:igdtList><fr:igdtListName/><fr:igdtListLine><fr:igdtQuantity/><fr:igdtName ref="kartoffel">Kartoffeln</fr:igdtName></fr:igdtListLine></fr:igdtList></fr:recipeIngredients><fr:recipeInstructions><fr:instruction><fr:instrStepName/><fr:instrStepText>Im September und October enthalten die Kartoffeln das meiste Mehl. Sie werden rein gewaschen, geschält, wieder gut gewaschen, auf einem Reibeisen gerieben, das Geriebene mit vielem Wasser durchgerührt und solches auf einen Durchschlag geschüttet. Das Durchgelaufene rührt man gut um, läßt es durch ein Haarsieb in ein sauberes, irdenes Geschirr laufen und stellt es an einen Ort, wo kein Staub hinein fallen kann. Hat sich das Mehl gesenkt, so schüttet man das Wasser davon ab, gibt frisches dazu und rührt das Mehl vom Boden los. So wiederholt man das Abschütten des Wassers und Losrühren des Mehles so lange, bis das Wasser ganz klar ist. Dann schüttet man es rein ab und läßt das Mehl etwas von der Luft antrocknen, schabt nun mit einem scharfen Löffel dasselbe ab und legt es zum Trocknen dünne auseinander. Ist das Mehl beinahe trocken, wird es mit einer Tortenrolle fein gerieben und vollends trocken gemacht, nur darf dies nicht am Ofen geschehen.</fr:instrStepText></fr:instruction></fr:recipeInstructions><fr:recipeSideDish/><fr:recipeOrigin/><fr:recipeSeeAlso/><fr:recipeLicense/></fr:recipe>