<?xml version="1.0" encoding="UTF-8"?><fr:recipe xmlns:fr="http://fruschtique.de/ns/recipe" xmlns:xsi="http://www.w3.org/2001/XMLSchema-instance" xsi:schemaLocation="http://fruschtique.de/ns/recipe file:///c:/Users/nlutt/Documents/websites/tools/recipe.xsd" rcpID="Q-105"><fr:meta><fr:book>KochbuchHD</fr:book><fr:chapter>15 Backwerk</fr:chapter></fr:meta><fr:recipeName>Theekuchen</fr:recipeName><fr:recipeKeywords/><fr:recipeIntro/><fr:recipeIngredients><fr:igdtList><fr:igdtListLine><fr:igdtQuantity>12 Loth</fr:igdtQuantity><fr:igdtName>Sahne</fr:igdtName></fr:igdtListLine><fr:igdtListLine><fr:igdtQuantity/><fr:igdtName>Butter</fr:igdtName></fr:igdtListLine><fr:igdtListLine><fr:igdtQuantity>2</fr:igdtQuantity><fr:igdtName>Eier</fr:igdtName></fr:igdtListLine><fr:igdtListLine><fr:igdtQuantity>2 EL</fr:igdtQuantity><fr:igdtName>Zucker</fr:igdtName></fr:igdtListLine><fr:igdtListLine><fr:igdtQuantity/><fr:igdtName>Zitronenschale</fr:igdtName></fr:igdtListLine><fr:igdtListLine><fr:igdtQuantity/><fr:igdtName>Blüthe</fr:igdtName></fr:igdtListLine><fr:igdtListLine><fr:igdtQuantity>2 Loth</fr:igdtQuantity><fr:igdtName>Hefen</fr:igdtName></fr:igdtListLine><fr:igdtListLine><fr:igdtQuantity>1 Pfund</fr:igdtQuantity><fr:igdtName>Mehl</fr:igdtName></fr:igdtListLine><fr:igdtListLine><fr:igdtQuantity/><fr:igdtName>Zimmet</fr:igdtName></fr:igdtListLine></fr:igdtList></fr:recipeIngredients><fr:recipeInstructions><fr:instruction><fr:instrStepName>Zubereitung</fr:instrStepName><fr:instrStepText>Zu 12 Loth zu Sahne geriebener Butter gibt man 2 Eier, 1 Tasse dicker Sahne, 2 gehäufte Eßlöffel Zucker, Zitronenschale oder Blüthe, 2 Loth zerrührter Hefen und 1 Pfund Mehl, macht einen Teig daraus, den man stark schlägt, einen Finger dick ausrollt oder auf einer Platte auseinanderdrückt, gut aufgehen läßt, mit 4 Loth geschmolzener Butter bestreicht, reichlich mit Zucker und Zimmet bestreut, und bei starker Hitze 15—20 Minuten backt. </fr:instrStepText></fr:instruction></fr:recipeInstructions></fr:recipe>