<?xml version="1.0" encoding="UTF-8"?><fr:recipe xmlns:fr="http://fruschtique.de/ns/recipe" xmlns:xsi="http://www.w3.org/2001/XMLSchema-instance" xsi:schemaLocation="http://fruschtique.de/ns/recipe file:///c:/Users/nlutt/Documents/websites/tools/recipe.xsd" rcpID="I-013">
<fr:meta><fr:book>KochbuchHD</fr:book><fr:chapter>08 Fleischspeisen aller Art</fr:chapter></fr:meta><fr:recipeName>Beefsteaks</fr:recipeName><fr:recipeKeywords/><fr:recipeIntro/><fr:recipeIngredients><fr:igdtList><fr:igdtListName/><fr:igdtListLine><fr:igdtQuantity/><fr:igdtName ref="rindfleisch">Mürbebraten</fr:igdtName></fr:igdtListLine><fr:igdtListLine><fr:igdtQuantity/><fr:igdtName ref="">Pfeffer</fr:igdtName></fr:igdtListLine><fr:igdtListLine><fr:igdtQuantity/><fr:igdtName ref="">Salz</fr:igdtName></fr:igdtListLine><fr:igdtListLine><fr:igdtQuantity/><fr:igdtName ref="butter">Butter</fr:igdtName></fr:igdtListLine></fr:igdtList></fr:recipeIngredients><fr:recipeInstructions><fr:instruction><fr:instrStepName>Zubereitung</fr:instrStepName><fr:instrStepText>Der Mürbebraten ist hierzu am besten. Er wird mit einem runden Klopfholz langsam geklopft, in zwei Finger dicke Scheiben geschnitten, diese werden mit Pfeffer und Salz bestreut, und gleich darauf in kochende Butter gelegt, bei raschem Feuer offen gebraten. Man läßt die Stücke ruhig liegen, bis sich oben etwas Blut zeigt, dann werden sie, ohne darin zu stechen, mit einem Messer umgelegt und wieder gebraten, bis man auch auf dieser Seite das Blut bemerkt. Darauf legt man sie schnell in eine heiße Schüssel, rührt etwas kaltes Wasser zu der Sauce und gießt dieselbe über das Fleisch. Nur muß man nicht viel Wasser nehmen, damit die Sauce gebunden werde. </fr:instrStepText><fr:instrStepText>Der Mürbebraten muß wenigstens im Winter 3—4 Tage alt sein, im Sommer kann man ihn nach 2 Tagen gebrauchen. </fr:instrStepText><fr:instrStepText>Zu jedem Pfunde Fleisch kann man zu gebratenen Beefsteaks ein knappes, zu geschmorten Beefsteaks 1 volles Loth Salz und 1/10 Loth Pfeffer rechnen. </fr:instrStepText></fr:instruction></fr:recipeInstructions><fr:recipeSideDish/><fr:recipeOrigin/><fr:recipeSeeAlso/><fr:recipeLicense/></fr:recipe>