<?xml version="1.0" encoding="UTF-8"?><!DOCTYPE stylesheet SYSTEM "file:///C:/Users/nlutt/Documents/Websites/tools/entities.dtd"><fr:recipe xmlns:fr="http://fruschtique.de/ns/recipe" xmlns:xsi="http://www.w3.org/2001/XMLSchema-instance" xsi:schemaLocation="http://fruschtique.de/ns/recipe file:///c:/Users/nlutt/Documents/websites/tools/recipe.xsd" rcpID="I-087">
<fr:meta><fr:book>KochbuchHD</fr:book><fr:chapter>08 Fleischspeisen aller Art</fr:chapter></fr:meta><fr:recipeName>Geklopfte Leber im Netz gebraten</fr:recipeName><fr:recipeKeywords></fr:recipeKeywords><fr:recipeIntro/><fr:recipeIngredients><fr:igdtList><fr:igdtListName></fr:igdtListName><fr:igdtListLine><fr:igdtQuantity></fr:igdtQuantity><fr:igdtName ref="leber">Leber</fr:igdtName></fr:igdtListLine><fr:igdtListLine><fr:igdtQuantity>¼ Pfund</fr:igdtQuantity><fr:igdtName ref="speck">Speck</fr:igdtName></fr:igdtListLine><fr:igdtListLine><fr:igdtQuantity>¼ Pfund</fr:igdtQuantity><fr:igdtName ref="knochenmark">Mark</fr:igdtName></fr:igdtListLine><fr:igdtListLine><fr:igdtQuantity>¼ Pfund</fr:igdtQuantity><fr:igdtName ref="butter">Butter</fr:igdtName></fr:igdtListLine><fr:igdtListLine><fr:igdtQuantity>4 Loth</fr:igdtQuantity><fr:igdtName ref="sultaninen">Korinthen</fr:igdtName></fr:igdtListLine><fr:igdtListLine><fr:igdtQuantity>6</fr:igdtQuantity><fr:igdtName ref="ei">Eier</fr:igdtName></fr:igdtListLine><fr:igdtListLine><fr:igdtQuantity>6 EL</fr:igdtQuantity><fr:igdtName ref="zwieback">Zwieback</fr:igdtName></fr:igdtListLine><fr:igdtListLine><fr:igdtQuantity></fr:igdtQuantity><fr:igdtName ref="piment">Nelkenpfeffer</fr:igdtName></fr:igdtListLine><fr:igdtListLine><fr:igdtQuantity>1</fr:igdtQuantity><fr:igdtName ref="zwiebel">Zwiebel</fr:igdtName></fr:igdtListLine><fr:igdtListLine><fr:igdtQuantity></fr:igdtQuantity><fr:igdtName ref="butter">Butter</fr:igdtName></fr:igdtListLine><fr:igdtListLine><fr:igdtQuantity>1 EL</fr:igdtQuantity><fr:igdtName ref="weizenmehl">Mehl</fr:igdtName></fr:igdtListLine><fr:igdtListLine><fr:igdtQuantity></fr:igdtQuantity><fr:igdtName ref="">Bratenbrühe</fr:igdtName></fr:igdtListLine><fr:igdtListLine><fr:igdtQuantity></fr:igdtQuantity><fr:igdtName ref="fleischbrühe">Bouillon</fr:igdtName></fr:igdtListLine><fr:igdtListLine><fr:igdtQuantity></fr:igdtQuantity><fr:igdtName ref="muskat">Muskat</fr:igdtName></fr:igdtListLine><fr:igdtListLine><fr:igdtQuantity></fr:igdtQuantity><fr:igdtName ref="piment">Nelkenpfeffer</fr:igdtName></fr:igdtListLine><fr:igdtListLine><fr:igdtQuantity></fr:igdtQuantity><fr:igdtName ref="zitrone">Zitronenscheiben</fr:igdtName></fr:igdtListLine><fr:igdtListLine><fr:igdtQuantity>1 Glas</fr:igdtQuantity><fr:igdtName ref="wein">Rothwein</fr:igdtName></fr:igdtListLine><fr:igdtListLine><fr:igdtQuantity>etwas</fr:igdtQuantity><fr:igdtName ref="zucker">Zucker</fr:igdtName></fr:igdtListLine></fr:igdtList></fr:recipeIngredients><fr:recipeInstructions><fr:instruction><fr:instrStepName>Zubereitung</fr:instrStepName><fr:instrStepText>Die Leber wird gewaschen, fein gehackt, das Häutige und die Adern herausgenommen. Dann vermischt man die durch ein Sieb gerührte Leber mit ¼ Pfund Speck und ¼ Pfund Mark, beides fein gehackt, oder statt letzterem ¼ Pfund zerrührte Butter, 4 Loth Korinthen, 6 Eidotter, etwa 6 Löffel voll gestoßenen Zwieback, Nelkenpfeffer und rührt zuletzt den Schaum der Eier eben durch. Nun läßt man Butter in einer Pfanne zergehn, legt das gereinigte Netz eines Kalbes hinein, die Masse darauf, das Netz wird von allen Seiten nach oben zusammengelegt, zugedeckt, auf beiden Seiten langsam ungefähr ½ Stunde gebraten und mit folgender Sauce angerichtet:. </fr:instrStepText><fr:instrStepText>Eine fein gehackte Zwiebel in Butter gebraten, mit einem Löffel Mehl bräunlich gemacht, Bratenbrühe oder Bouillon, Muskat, Nelkenpfeffer, Zitronenscheiben, ein Glas Rothwein und etwas Zucker dazu gegeben und durchgekocht. </fr:instrStepText></fr:instruction></fr:recipeInstructions><fr:recipeSideDish></fr:recipeSideDish><fr:recipeOrigin></fr:recipeOrigin><fr:recipeSeeAlso></fr:recipeSeeAlso><fr:recipeLicense></fr:recipeLicense></fr:recipe>