<?xml version="1.0" encoding="UTF-8"?><fr:recipe xmlns:fr="http://fruschtique.de/ns/recipe" xmlns:xsi="http://www.w3.org/2001/XMLSchema-instance" xsi:schemaLocation="http://fruschtique.de/ns/recipe file:///c:/Users/nlutt/Documents/websites/tools/recipe.xsd" rcpID="N-15"><fr:meta><fr:book>KochbuchHD</fr:book><fr:chapter>12 Compotes</fr:chapter></fr:meta><fr:recipeName>Johannisbeeren und Himbeeren</fr:recipeName><fr:recipeKeywords/><fr:recipeIntro/><fr:recipeIngredients><fr:igdtList><fr:igdtListLine><fr:igdtQuantity>1</fr:igdtQuantity><fr:igdtName>Zucker</fr:igdtName></fr:igdtListLine><fr:igdtListLine><fr:igdtQuantity/><fr:igdtName>Beeren</fr:igdtName></fr:igdtListLine><fr:igdtListLine><fr:igdtQuantity/><fr:igdtName>Schaumlöffel</fr:igdtName></fr:igdtListLine><fr:igdtListLine><fr:igdtQuantity/><fr:igdtName>Syrup</fr:igdtName></fr:igdtListLine><fr:igdtListLine><fr:igdtQuantity/><fr:igdtName>Compot</fr:igdtName></fr:igdtListLine></fr:igdtList></fr:recipeIngredients><fr:recipeInstructions><fr:instruction><fr:instrStepName>Zubereitung</fr:instrStepName><fr:instrStepText>Werden mit einer Gabel von den Stielen gestreift, nicht gewaschen, mit vielem gestoßenen Zucker lagenweise durchstreut, nicht länger gekocht, bis die Beeren eben weich sind, und schnell mit dem Schaumlöffel herausgenommen. Dann wird der Saft Syrup ähnlich eingekocht und abgekühlt über das Compot gegeben. </fr:instrStepText></fr:instruction></fr:recipeInstructions></fr:recipe>