<?xml version="1.0" encoding="UTF-8"?>
<!DOCTYPE stylesheet SYSTEM "file:///C:/Users/nlutt/Documents/Websites/tools/entities.dtd">
<fr:recipe xmlns:fr="http://fruschtique.de/ns/recipe" xmlns:xsi="http://www.w3.org/2001/XMLSchema-instance" xsi:schemaLocation="http://fruschtique.de/ns/recipe ../../../tools/recipe.xsd" rcpID="F-7">
<fr:meta><fr:book>KochbuchHD</fr:book><fr:chapter>05 Aufläufe</fr:chapter></fr:meta><fr:recipeName>Mehl-Auflauf</fr:recipeName><fr:recipeKeywords></fr:recipeKeywords><fr:recipeIntro/><fr:recipeIngredients><fr:igdtList noshow="noshow" fromRecipe="Schwamm-Pudding" fromRcpID="E-17" fromBook="KochbuchHD" fromChapter="04 Puddings"><fr:igdtListName>Schwamm-Pudding</fr:igdtListName><fr:igdtListLine><fr:igdtQuantity>12 Loth</fr:igdtQuantity><fr:igdtName ref="">Mehl</fr:igdtName></fr:igdtListLine><fr:igdtListLine><fr:igdtQuantity>10</fr:igdtQuantity><fr:igdtName ref="">Eier</fr:igdtName></fr:igdtListLine><fr:igdtListLine><fr:igdtQuantity>8 Loth</fr:igdtQuantity><fr:igdtName ref="">Butter</fr:igdtName></fr:igdtListLine><fr:igdtListLine><fr:igdtQuantity>6 Loth</fr:igdtQuantity><fr:igdtName ref="">Zucker</fr:igdtName></fr:igdtListLine><fr:igdtListLine><fr:igdtQuantity>1</fr:igdtQuantity><fr:igdtName ref="">Zitrone</fr:igdtName></fr:igdtListLine><fr:igdtListLine><fr:igdtQuantity>¼ Maß</fr:igdtQuantity><fr:igdtName ref="">Milch</fr:igdtName></fr:igdtListLine><fr:igdtListLine><fr:igdtQuantity></fr:igdtQuantity><fr:igdtName ref="">Sahne</fr:igdtName></fr:igdtListLine><fr:igdtListLine><fr:igdtQuantity></fr:igdtQuantity><fr:igdtName ref="">Gewürz</fr:igdtName></fr:igdtListLine><fr:igdtListLine><fr:igdtQuantity></fr:igdtQuantity><fr:igdtName ref="">Eidotter</fr:igdtName></fr:igdtListLine></fr:igdtList></fr:recipeIngredients><fr:recipeInstructions><fr:instruction><fr:instrStepName>Zubereitung</fr:instrStepName><fr:instrStepText>Dieselbe Masse, wie zum Schwamm-Pudding; wird eine Stunde gebacken. Siehe E Nro. 17.</fr:instrStepText></fr:instruction></fr:recipeInstructions><fr:recipeSideDish></fr:recipeSideDish><fr:recipeOrigin></fr:recipeOrigin><fr:recipeSeeAlso></fr:recipeSeeAlso><fr:recipeLicense></fr:recipeLicense></fr:recipe>